dghello/Hello.py
dghello/__init__.py
dghello-0.1.1.dist-info/LICENSE
dghello-0.1.1.dist-info/METADATA
dghello-0.1.1.dist-info/WHEEL
dghello-0.1.1.dist-info/top_level.txt
dghello-0.1.1.dist-info/RECORD
