Metadata-Version: 2.1
Name: dghello
Version: 0.1.1
Summary: Test package for github and PyPi
Home-page: https://github.com/dgroner/dghello
Author: Daniel Groner
Author-email: dgroner@fordham.edu
License: MIT
Keywords: DGHELLO,GRONER
Platform: UNKNOWN
Classifier: Development Status :: 3 - Alpha
Classifier: Intended Audience :: Developers
Classifier: Topic :: Software Development :: Build Tools
Classifier: License :: OSI Approved :: MIT License
Classifier: Programming Language :: Python :: 3
Classifier: Operating System :: OS Independent
Requires-Python: >=3.6
